[
  {
    "venue": "浜松",
    "grade": "",
    "races": [
      {
        "race_number": 1,
        "start_time": "10:46",
        "closed_at": "10:44",
        "players": [
          "1中野肇",
          "2橋本優一",
          "3中村晋典",
          "4吉田幸司",
          "5稲川聖也",
          "6山崎進",
          "7佐藤大地",
          "8佐藤励"
        ],
        "class_category": "予選"
      },
      {
        "race_number": 2,
        "start_time": "11:11",
        "closed_at": "11:09",
        "players": [
          "1瀬戸尾侑宏",
          "2金子和裕",
          "3柴田紘志",
          "4関口隆広",
          "5和田健吾",
          "6藤波直也",
          "7掛川和人",
          "8落合巧"
        ],
        "class_category": "予選"
      },
      {
        "race_number": 3,
        "start_time": "11:37",
        "closed_at": "11:35",
        "players": [
          "1脇川大樹",
          "2島田健一",
          "3鈴木景斗",
          "4伊東玲衣",
          "5岡谷美由紀",
          "6山浦博幸",
          "7岩科鮮太",
          "8伊藤信夫"
        ],
        "class_category": "予選"
      },
      {
        "race_number": 4,
        "start_time": "12:05",
        "closed_at": "12:03",
        "players": [
          "1宮司佳奈",
          "2斎藤隆充",
          "3本田仁恵",
          "4今田真輔",
          "5鈴木静二",
          "6川原剛",
          "7仲口武志",
          "8吉林直都"
        ],
        "class_category": "予選"
      },
      {
        "race_number": 5,
        "start_time": "12:36",
        "closed_at": "12:34",
        "players": [
          "1広瀬豪彦",
          "2日室志郎",
          "3北市唯",
          "4深沢隆",
          "5梅内幹雄",
          "6君和田裕二",
          "7花田一輝",
          "8鈴木宏和"
        ],
        "class_category": "予選"
      },
      {
        "race_number": 6,
        "start_time": "13:06",
        "closed_at": "13:04",
        "players": [
          "1柴本真樹",
          "2高橋祐一",
          "3重富英雄",
          "4相馬康夫",
          "5赤堀翼",
          "6吉田祐也",
          "7岩田裕臣",
          "8青島正樹"
        ],
        "class_category": ""
      },
      {
        "race_number": 7,
        "start_time": "13:36",
        "closed_at": "13:34",
        "players": [
          "1岸田大知",
          "2畦坪孝雄",
          "3信沢綾乃",
          "4西川頼臣",
          "5浅野浩幸",
          "6福田裕二",
          "7遠藤誠",
          "8木村武之"
        ],
        "class_category": ""
      },
      {
        "race_number": 8,
        "start_time": "14:07",
        "closed_at": "14:05",
        "players": [
          "1吉田富重",
          "2鈴木章夫",
          "3石井大志",
          "4早津圭介",
          "5高石光将",
          "6穴見和正",
          "7佐藤裕二",
          "8佐藤貴也"
        ],
        "class_category": "予選"
      },
      {
        "race_number": 9,
        "start_time": "14:38",
        "closed_at": "14:36",
        "players": [
          "1鈴木啓示",
          "2竹中一成",
          "3角貝拓海",
          "4鈴木健吾",
          "5谷島俊行",
          "6柴田健治",
          "7掛川和人",
          "8金子大輔"
        ],
        "class_category": "予選"
      },
      {
        "race_number": 10,
        "start_time": "15:10",
        "closed_at": "15:08",
        "players": [
          "1縫田雅一",
          "2山脇孝志",
          "3田中崇太",
          "4長谷晴久",
          "5岡谷美由紀",
          "6森下輝",
          "7松山茂靖",
          "8佐藤励"
        ],
        "class_category": "予選"
      },
      {
        "race_number": 11,
        "start_time": "15:44",
        "closed_at": "15:42",
        "players": [
          "1城山英文",
          "2岩佐常義",
          "3桝崎星名",
          "4田方秀和",
          "5鈴木一馬",
          "6武藤博臣",
          "7青木治親",
          "8鈴木圭一郎"
        ],
        "class_category": "予選"
      },
      {
        "race_number": 12,
        "start_time": "16:20",
        "closed_at": "16:18",
        "players": [
          "1塚本浩司",
          "2木村直幸",
          "3小林頼介",
          "4押田幸夫",
          "5西翔子",
          "6石貝武之",
          "7山本将之",
          "8黒川京介"
        ],
        "class_category": "予選"
      }
    ]
  },
  {
    "venue": "山陽",
    "grade": "",
    "races": [
      {
        "race_number": 1,
        "start_time": "19:53",
        "closed_at": "19:51",
        "players": [
          "1片岡信之",
          "2猪熊龍太",
          "3山本智大",
          "4中村浩章",
          "5三宅真央",
          "6小栗勝太"
        ],
        "class_category": "一般"
      },
      {
        "race_number": 2,
        "start_time": "20:20",
        "closed_at": "20:18",
        "players": [
          "1小松俊輔",
          "2別府末彦",
          "3小田雄一朗",
          "4清岡優一",
          "5佐伯拓実",
          "6深谷俊太"
        ],
        "class_category": "一般"
      },
      {
        "race_number": 3,
        "start_time": "20:48",
        "closed_at": "20:46",
        "players": [
          "1小川可蓮",
          "2石橋大",
          "3戸塚茂",
          "4佐藤智也",
          "5下平佳輝",
          "6福永貴史"
        ],
        "class_category": "一般"
      },
      {
        "race_number": 4,
        "start_time": "21:16",
        "closed_at": "21:14",
        "players": [
          "1田中竜二",
          "2宍戸幸雄",
          "3安東久隆",
          "4北爪勝義",
          "5筒井健太",
          "6高木健太郎"
        ],
        "class_category": "一般"
      },
      {
        "race_number": 5,
        "start_time": "21:44",
        "closed_at": "21:42",
        "players": [
          "1伊藤幸人",
          "2千葉泰将",
          "3深沢悟",
          "4青嶋裕治",
          "5辰巳裕樹",
          "6小栗勝太"
        ],
        "class_category": "一般"
      },
      {
        "race_number": 6,
        "start_time": "22:12",
        "closed_at": "22:10",
        "players": [
          "1松本渉",
          "2猪熊龍太",
          "3磯部真樹",
          "4清岡優一",
          "5稲原良太郎",
          "6西村龍太郎"
        ],
        "class_category": "一般"
      },
      {
        "race_number": 7,
        "start_time": "22:40",
        "closed_at": "22:38",
        "players": [
          "1滝谷圭",
          "2池田康範",
          "3松生信二",
          "4西村義正",
          "5矢野正剛",
          "6五所淳"
        ],
        "class_category": "選抜"
      },
      {
        "race_number": 8,
        "start_time": "23:08",
        "closed_at": "23:06",
        "players": [
          "1日名子幹正",
          "2林弘明",
          "3緒方浩一",
          "4永島潤太郎",
          "5藤岡一樹",
          "6中村友和"
        ],
        "class_category": "特別"
      },
      {
        "race_number": 9,
        "start_time": "23:40",
        "closed_at": "23:38",
        "players": [
          "1丹下昂紀",
          "2藤本悠仁",
          "3植村愛悠斗",
          "4松井大和",
          "5春本綾斗",
          "6丹村飛竜"
        ],
        "class_category": "優勝戦"
      }
    ]
  }
]